goodip/__init__.py
goodip/exceptions.py
goodip/ip.py
goodip-0.0.5.dist-info/LICENSE
goodip-0.0.5.dist-info/METADATA
goodip-0.0.5.dist-info/WHEEL
goodip-0.0.5.dist-info/top_level.txt
goodip-0.0.5.dist-info/RECORD
