Metadata-Version: 2.1
Name: goodip
Version: 0.0.5
Summary: you can get your ip address and get its information.
Home-page: https://github.com/Erfan-Bafandeh/goodip
Author: Erfan Bafandeh
Author-email: user.enbh@gmail.com
Keywords: ip,myip,goodip,checkip
Classifier: Programming Language :: Python :: 3.6
Classifier: Programming Language :: Python :: 3.7
Classifier: Programming Language :: Python :: 3.8
Classifier: Programming Language :: Python :: 3.9
Classifier: Programming Language :: Python :: 3.10
Classifier: Programming Language :: Python :: 3.11
Classifier: Programming Language :: Python :: 3.12
Classifier: License :: OSI Approved :: MIT License
Requires-Python: ~=3.6
License-File: LICENSE
Requires-Dist: requests
Requires-Dist: beautifulsoup4
